{
  "current": {
    "color_default": "#c83a3a",
    "color_primary": "#7db641",
    "color_borders": "#ebebeb",
    "color_link": "#000000",
    "color_heading_text": "#000000",
    "color_body_text": "#000000",
    "header_background_color": "#ffffff",
    "color_topbar_text": "#868686",
    "color_nav_text": "#ffffff",
    "color_sub_nav_bg": "#ffffff",
    "color_sub_nav_text": "#000000",
    "color_footer_bg": "#ffffff",
    "color_footer_title_text": "#000",
    "color_footer_text": "#7e7f80",
    "color_footer_bg_bottom": "rgba(0,0,0,0)",
    "copyright_text_color": "#aeb7b5",
    "color_cart": "#7db641",
    "color_support": "#c83a3a",
    "bg_feature": "#f84f4f",
    "color_price": "#ea3018",
    "bg_save_label": "#f13340",
    "body_font": "Roboto Slab",
    "heading_font": "Roboto Slab",
    "menu_font": "Roboto Slab",
    "product_font": "Roboto Slab",
    "button_font": "Roboto Slab",
    "enable_medium_layout": false,
    "newsletter_form_action": "",
    "display_backtop": true,
    "enable_megamenu_item_1": true,
    "megamenu_1_parent": "categories",
    "widget_linklist_megamenu_1_1": "categories",
    "menuitem_col_link_1_1": "three-twelfths",
    "widget_linklist_megamenu_2_1": "chocolate",
    "menuitem_col_link_2_1": "three-twelfths",
    "widget_linklist_megamenu_3_1": "",
    "menuitem_col_link_3_1": "three-twelfths",
    "widget_linklist_megamenu_4_1": "",
    "menuitem_col_link_4_1": "three-twelfths",
    "widget_linklist_megamenu_5_1": "",
    "menuitem_col_link_5_1": "three-twelfths",
    "enable_custom_menu_1": true,
    "widget_custom_megamenu_1": "<iframe src=\"https:\/\/player.vimeo.com\/video\/43457382\" width=\"640\" height=\"360\" frameborder=\"0\">\r\n<\/iframe>",
    "menuitem_col_link_6_1": "six-twelfths",
    "enable_megamenu_item_2": true,
    "megamenu_2_parent": "community",
    "widget_linklist_megamenu_1_2": "information-1",
    "menuitem_col_link_1_2": "three-twelfths",
    "widget_linklist_megamenu_2_2": "trends-events",
    "menuitem_col_link_2_2": "three-twelfths",
    "widget_linklist_megamenu_3_2": "your-account",
    "menuitem_col_link_3_2": "three-twelfths",
    "widget_linklist_megamenu_4_2": "our-offers",
    "menuitem_col_link_4_2": "three-twelfths",
    "widget_linklist_megamenu_5_2": "",
    "menuitem_col_link_5_2": "one-twelfth",
    "enable_custom_menu_2": false,
    "widget_custom_megamenu_2": "",
    "menuitem_col_link_6_2": "one-twelfth",
    "enable_megamenu_item_3": false,
    "megamenu_3_parent": "",
    "widget_linklist_megamenu_1_3": "",
    "menuitem_col_link_1_3": "one-twelfth",
    "widget_linklist_megamenu_2_3": "",
    "menuitem_col_link_2_3": "one-twelfth",
    "widget_linklist_megamenu_3_3": "",
    "menuitem_col_link_3_3": "one-twelfth",
    "widget_linklist_megamenu_4_3": "",
    "menuitem_col_link_4_3": "one-twelfth",
    "widget_linklist_megamenu_5_3": "",
    "menuitem_col_link_5_3": "one-twelfth",
    "enable_custom_menu_3": false,
    "widget_custom_megamenu_3": "",
    "menuitem_col_link_6_3": "one-twelfth",
    "enable_megamenu_item_4": false,
    "megamenu_4_parent": "",
    "widget_linklist_megamenu_1_4": "",
    "menuitem_col_link_1_4": "one-twelfth",
    "widget_linklist_megamenu_2_4": "",
    "menuitem_col_link_2_4": "one-twelfth",
    "widget_linklist_megamenu_3_4": "",
    "menuitem_col_link_3_4": "one-twelfth",
    "widget_linklist_megamenu_4_4": "",
    "menuitem_col_link_4_4": "one-twelfth",
    "widget_linklist_megamenu_5_4": "",
    "menuitem_col_link_5_4": "one-twelfth",
    "enable_custom_menu_4": false,
    "widget_custom_megamenu_4": "",
    "menuitem_col_link_6_4": "one-twelfth",
    "enable_megamenu_item_5": false,
    "megamenu_5_parent": "",
    "megamenu_custom_html_5": "hello world",
    "enable_megamenu_item_6": false,
    "megamenu_6_parent": "",
    "megamenu_custom_html_6": "",
    "logo_use_image": true,
    "logo_max_width": "450",
    "favicon_enable": false,
    "enable_header_phone": true,
    "header_phone_title": "CALL TOLL FREE",
    "header_phone_number": "1800 - 123 - COFFEEIS",
    "enable_free_delivery": true,
    "free_delivery_title": "FREE DELIVERY",
    "free_delivery_number": "ON ORDER OVER <span>$7.00<\/span>",
    "enable_footer_top": true,
    "footer_custom_title": "<span>Custom<\/span> Block",
    "footer_custom_content": "<img src=\"https:\/\/cdn.shopify.com\/s\/files\/1\/1466\/3512\/files\/customimage.png\">\r\n Proin gravida nibh vel velit auctor aliquet aene  feugiat, velit mauris egestas quam, ut aliquam massa nisl quis neque isl quis neque.  ut aliquam massa nisl quis velit mauris egestas",
    "footer_gallery_title": "<span>Blog<\/span> Gallery",
    "blogs_gallery_select": "gallery",
    "blogs_gallery_num": "3",
    "blogs_gallery_limit": "9",
    "footer_twitter_title": "<span>Latest<\/span> tweets",
    "twitter_widget": "<a class=\"twitter-timeline\" href=\"https:\/\/twitter.com\/junotheme\"><\/a> <script async src=\"\/\/platform.twitter.com\/widgets.js\" charset=\"utf-8\"><\/script>",
    "height_twitter": "277px",
    "footer_blog_title": "<span>Lastest<\/span> blog",
    "home_blogs_select": "news",
    "home_blogs_limit": "3",
    "footer_contact_title": "About store",
    "footer_contact": "<ul class=\"contact-us\">\r\n<li>\r\n<i class=\"fa fa-map-marker\"><\/i>\r\nGear Store\r\nNo 40 Baria Sreet 133\/2 New York City, NY, United States\r\n<\/li>\r\n<li>\r\n<i class=\"fa fa-mobile\"><\/i>\r\nPhone: 0123-456-789\r\n<\/li>\r\n<li>\r\n<i class=\"fa fa-envelope\"> <\/i>\r\ninfo@junothemes.com\r\n<\/li>\r\n<\/ul>",
    "footer_menu_1_enable": true,
    "footer_menu_1_title": "Services",
    "footer_menu_1": "services",
    "footer_menu_2_enable": true,
    "footer_menu_2_title": "About us",
    "footer_menu_2": "about-us-2",
    "footer_menu_3_enable": true,
    "footer_menu_3_title": "INFORMATION",
    "footer_menu_3": "information",
    "footer_newsletter_enable": true,
    "footer_newsletter_title": "Newsletter",
    "footer_newsletter_content": "Make sure you dont miss interesting happenings by joining our newsletter program. We dont do spam. Ever. Because that sucks.",
    "footer_menu_4": "footer",
    "copyright_content": "Designed By Junothemes.",
    "footer_payment_title": "",
    "payment_enable_1": true,
    "payment_url1": "#",
    "payment_enable_2": true,
    "payment_url2": "#",
    "payment_enable_3": true,
    "payment_url3": "",
    "payment_enable_4": true,
    "payment_url4": "#",
    "payment_enable_5": true,
    "payment_url5": "#",
    "payment_enable_6": true,
    "payment_url6": "#",
    "payment_enable_7": true,
    "payment_url7": "#",
    "popup_newsletter_enable": true,
    "popup_newsletter_title": "newsletter",
    "popup_newsletter_subtitle": "welcome to our site!",
    "popup_newsletter_description": "Subscribe to our newsletter and don’t miss new arrivals, the latest update and our promotions.",
    "newsletter_popup_seconds": "0",
    "newsletter_popup_days": "2",
    "cart_notes_enable": true,
    "cart_vendor_enable": false,
    "ajax_cart_method": "drawer",
    "show_social": true,
    "social_facebook_link": "#",
    "social_twitter_link": "#",
    "social_pinterest_link": "",
    "social_instagram_link": "#",
    "social_google_plus_link": "#",
    "social_tumblr_link": "#",
    "social_youtube_link": "",
    "social_vimeo_link": "",
    "twittercard_handle": "@",
    "social_sharing_products": true,
    "social_sharing_blog": true,
    "social_sharing_style": "is-default",
    "share_primary_color": false,
    "share_choose_color": "$colorBtnPrimary",
    "share_facebook": true,
    "share_twitter": true,
    "share_pinterest": true,
    "share_fancy": true,
    "share_google": true,
    "home_section_1": "section-slideshow",
    "home_section_2": "section-banner-2-col-top",
    "home_section_3": "section-product-new",
    "home_section_4": "section-product-new2",
    "home_section_5": "section-banner-3-col-2",
    "slideshow_time": "8000",
    "slider_startwidth": "870",
    "slider_startheight": "445",
    "slide_1_enable": true,
    "slide_1_transition": "slideup",
    "slide_1_heading": "NEQUE PORRO",
    "slide_1_headingEffect": "sfb",
    "slide_1_heading_y": "132",
    "slide_1_heading_x": "530",
    "slide_1_heading_spacing": "0",
    "slide_1_text": "Duis cursus ante nec dictum tincidunere <br> vulputate nisl quis gravida diam.",
    "slide_1_textEffect": "sfb",
    "slide_1_text_y": "188",
    "slide_1_text_x": "530",
    "slide_1_text_spacing": "0",
    "slide_1_show_category": false,
    "slide_1_button_category": "Browse category",
    "slide_1_button_category_link": "#",
    "slide_1_category_y": "201",
    "slide_1_category_x": "180",
    "slide_1_button_text": "Shop now",
    "slide_1_buttonEffect": "sfb",
    "slide_1_button_link": "#",
    "slide_1_button_y": "240",
    "slide_1_button_x": "530",
    "slide_1_heading_color": "#292929",
    "slide_1_text_color": "#ffffff",
    "slide_1_button_color": "#ffffff",
    "slide_1_heading_font_size": "36px",
    "slide_1_text_font_size": "12px",
    "slide_1_button_size": "14px",
    "slide_2_enable": true,
    "slide_2_transition": "random",
    "slide_2_heading": "NEQUE PORRO",
    "slide_2_headingEffect": "sfb",
    "slide_2_heading_y": "132",
    "slide_2_heading_x": "530",
    "slide_2_heading_spacing": "0px",
    "slide_2_text": "Duis cursus ante nec dictum tincidunere <br> vulputate nisl quis gravida diam.",
    "slide_2_textEffect": "sfb",
    "slide_2_text_y": "188",
    "slide_2_text_x": "530",
    "slide_2_text_spacing": "0px",
    "slide_2_show_category": false,
    "slide_2_category_y": "",
    "slide_2_category_x": "",
    "slide_2_button_category": "Browse category",
    "slide_2_button_category_link": "#",
    "slide_2_button_text": "Shop now",
    "slide_2_buttonEffect": "sfb",
    "slide_2_button_link": "#",
    "slide_2_button_y": "240",
    "slide_2_button_x": "530",
    "slide_2_heading_color": "#1c1818",
    "slide_2_text_color": "#ffffff",
    "slide_2_button_color": "#ffffff",
    "slide_2_heading_font_size": "36px",
    "slide_2_text_font_size": "12px",
    "slide_2_button_size": "14px",
    "slide_3_enable": true,
    "slide_3_transition": "random",
    "slide_3_heading": "NEQUE PORRO",
    "slide_3_headingEffect": "sfb",
    "slide_3_heading_y": "132",
    "slide_3_heading_x": "530",
    "slide_3_heading_spacing": "0",
    "slide_3_text": "Duis cursus ante nec dictum tincidunere <br> vulputate nisl quis gravida diam.",
    "slide_3_textEffect": "sfb",
    "slide_3_text_y": "188",
    "slide_3_text_x": "530",
    "slide_3_text_spacing": "0px",
    "slide_3_show_category": false,
    "slide_3_category_y": "",
    "slide_3_category_x": "",
    "slide_3_button_category": "Browse category",
    "slide_3_button_category_link": "#",
    "slide_3_button_text": "Shop now",
    "slide_3_buttonEffect": "sft",
    "slide_3_button_link": "#",
    "slide_3_button_y": "240",
    "slide_3_button_x": "530",
    "slide_3_heading_color": "#1a1717",
    "slide_3_text_color": "#ffffff",
    "slide_3_button_color": "#ffffff",
    "slide_3_heading_font_size": "36px",
    "slide_3_text_font_size": "12px",
    "slide_3_button_size": "14px",
    "slide_4_enable": false,
    "slide_4_transition": "random",
    "slide_4_heading": "SONY XPERIA",
    "slide_4_headingEffect": "sfb",
    "slide_4_heading_y": "40px",
    "slide_4_heading_x": "30px",
    "slide_4_heading_spacing": "0px",
    "slide_4_text": "Lorem ipsum dolor consectetur adipiscing elit enean <br> sapien massa posuquis quam non dui rutrum ornare sed sodales ectus <br>et ornare vivamus non pulvinar lacus",
    "slide_4_textEffect": "sfb",
    "slide_4_text_y": "100px",
    "slide_4_text_x": "30px",
    "slide_4_text_spacing": "0px",
    "slide_4_show_category": true,
    "slide_4_category_y": "200px",
    "slide_4_category_x": "150px",
    "slide_4_button_category": "Browse category",
    "slide_4_button_category_link": "#",
    "slide_4_button_text": "Shop now",
    "slide_4_buttonEffect": "sfb",
    "slide_4_button_link": "#",
    "slide_4_button_y": "200px",
    "slide_4_button_x": "30px",
    "slide_4_heading_color": "#ffffff",
    "slide_4_text_color": "#ffffff",
    "slide_4_button_color": "#000000",
    "slide_4_heading_font_size": "20px",
    "slide_4_text_font_size": "110px",
    "slide_4_button_size": "14px",
    "slide_5_enable": false,
    "slide_5_transition": "random",
    "slide_5_heading": "",
    "slide_5_headingEffect": "sfb",
    "slide_5_heading_y": "",
    "slide_5_heading_x": "",
    "slide_5_heading_spacing": "",
    "slide_5_text": "",
    "slide_5_textEffect": "sfb",
    "slide_5_text_y": "",
    "slide_5_text_x": "",
    "slide_5_text_spacing": "",
    "slide_5_show_category": false,
    "slide_5_category_y": "",
    "slide_5_category_x": "",
    "slide_5_button_category": "",
    "slide_5_button_category_link": "",
    "slide_5_button_text": "Shop now",
    "slide_5_buttonEffect": "sfb",
    "slide_5_button_link": "",
    "slide_5_button_y": "",
    "slide_5_button_x": "",
    "slide_5_heading_color": "#ffffff",
    "slide_5_text_color": "#ffffff",
    "slide_5_button_color": "#ffffff",
    "slide_5_heading_font_size": "",
    "slide_5_text_font_size": "",
    "slide_5_button_size": "",
    "select_effect_banner_2_0": "effect-v7",
    "banner_2_image_1_url_0": "#",
    "banner_2_image_2_url_0": "#",
    "new_owl_checked": true,
    "new_arrival_collection": "featured-product",
    "new_arrival_title": "<span>Top<\/span> Seller",
    "new_arrival_num": "4",
    "new_arrival_limit": "12",
    "new_owl_checked2": true,
    "new_arrival_collection2": "featured-product",
    "new_arrival_title2": "<span>Featured<\/span> Product",
    "new_arrival_num2": "4",
    "new_arrival_limit2": "8",
    "select_effect_bannerv2": "effect-v5",
    "banner_3_image_1v2_url": "#",
    "banner_3_image_2v2_url": "#",
    "banner_3_image_3v2_url": "#",
    "enable_box_1": true,
    "title_services_1": "Our Menu",
    "des_services_1": "Proin gravida nibh velit auctor auctor a ornare odio.",
    "feature_url_1": "#",
    "enable_box_2": true,
    "title_services_2": "Our Wines",
    "des_services_2": "Proin gravida nibh velit auctor auctor a ornare odio.",
    "feature_url_2": "#",
    "enable_box_3": true,
    "title_services_3": "Meet the Team",
    "des_services_3": "Proin gravida nibh velit auctor auctor a ornare odio.",
    "feature_url_3": "#",
    "enable_box_4": true,
    "title_services_4": "Where to find us",
    "des_services_4": "Proin gravida nibh velit auctor ornare odio.",
    "feature_url_4": "#",
    "nb_column": "4",
    "nb_per_page": "24",
    "product_show_swatch": true,
    "nb_thumbnail_visible": "5",
    "display_sample_vendor": false,
    "display_availability": true,
    "display_product_type": true,
    "display_vendor": true,
    "show_desc": "short",
    "show_product_swatch": false,
    "display_wishlist": true,
    "display_category": true,
    "display_tag": true,
    "display_des": true,
    "show_shipping_tab": true,
    "shipping_tab_title": "Shipping and Return",
    "shipping_tab_content": "<b>Returns Policy<\/b><br>\r\n<p>You may return most new, unopened items within 30 days of delivery for a full refund. We'll also pay the return shipping costs if the return is a result of our error (you received an incorrect or defective item, etc.).<\/p>\r\n\r\n<p>You should expect to receive your refund within four weeks of giving your package to the return shipper, however, in many cases you will receive a refund more quickly. This time period includes the transit time for us to receive your return from the shipper (5 to 10 business days), the time it takes us to process your return once we receive it (3 to 5 business days), and the time it takes your bank to process our refund request (5 to 10 business days).<\/p>\r\n\r\n<p>If you need to return an item, simply login to your account, view the order using the 'Complete Orders' link under the My Account menu and click the Return Item(s) button. We'll notify you via e-mail of your refund once we've received and processed the returned item.<\/p>\r\n\r\n<b>Shipping<\/b><br>\r\n<p>We can ship to virtually any address in the world. Note that there are restrictions on some products, and some products cannot be shipped to international destinations.<\/p>\r\n\r\n<p>When you place an order, we will estimate shipping and delivery dates for you based on the availability of your items and the shipping options you choose. Depending on the shipping provider you choose, shipping date estimates may appear on the shipping quotes page.<\/p>\r\n\r\n<p>Please also note that the shipping rates for many items we sell are weight-based. The weight of any such item can be found on its detail page. To reflect the policies of the shipping companies we use, all weights will be rounded up to the next full po<\/p>",
    "show_size_chart_tab": true,
    "size_chart_tab_title": "Size Chart",
    "display_reviews": true,
    "display_prev_next_product": true,
    "display_relate_products": true,
    "related_col": "5",
    "related_limit": "12",
    "blog_per_page": "8",
    "blog_per_row": "2",
    "blog_nosidebar_per_row": "3",
    "blog_gallery_per_row": "4",
    "enable_recent_article": true,
    "enable_categories": true,
    "enable_tags": true,
    "enable_instagram": true,
    "instagram_title": "Instagram",
    "instagram_content": "<!-- SnapWidget -->\r\n<script src=\"https:\/\/snapwidget.com\/js\/snapwidget.js\"><\/script>\r\n<iframe src=\"https:\/\/snapwidget.com\/embed\/171472\" class=\"snapwidget-widget\"  style=\"border:none; overflow:hidden; width:100%; \"><\/iframe>",
    "filter_enable": false,
    "filter_title": "Filters By",
    "enable_shop_by_tags_1": true,
    "shop_by_tags_1_title": "Color",
    "shop_by_color_text_1": "sliver",
    "shop_by_color_text_2": "blue",
    "shop_by_color_text_3": "white",
    "shop_by_color_text_4": "pink",
    "shop_by_color_text_5": "green",
    "shop_by_color_text_6": "black",
    "shop_by_color_text_7": "gray",
    "shop_by_color_text_8": "gold",
    "shop_by_color_text_9": "",
    "shop_by_color_text_10": "",
    "enable_shop_by_tags_2": false,
    "shop_by_tags_2_title": "Price",
    "shop_by_tags_2_list_tags": "1$-100$,101$-200$,201$-300$",
    "enable_shop_by_tags_4": true,
    "shop_by_tags_4_title": "Storage size",
    "shop_by_tags_4_list_tags": "16GB,32GB,64GB,128GB",
    "enable_shop_by_tags_5": true,
    "shop_by_tags_5_title": "Brand",
    "shop_by_tags_5_list_tags": "Apple, Samsung, HTC, Nokia, Lenovo",
    "display_categories_sidebar": true,
    "categories_title": "Categories",
    "categories_content": "custom",
    "categoies_menu": "categories",
    "widget_enable_1": true,
    "widget_title_1": "New Products",
    "widget_collection_1": "bestseller",
    "number_collection_1": "4",
    "widget_enable_2": false,
    "widget_title_2": "Bestseller",
    "widget_collection_2": "",
    "number_collection_2": "3",
    "brands_enable": false,
    "ads_enable": true,
    "ads_block_url": "#",
    "custom_cms_enable": false,
    "custom_cms_title": "Custom cms widget",
    "custom_cms_content": "<em>Custom CMS block displayed at the left sidebar on the Catalog Page. Put your own content here: text, html, images, media... whatever you like.<\/em><br><br><em>There are many similar sample content placeholders across the store. All editable from admin panel.<\/em>",
    "tags_enable": false,
    "contact_map": true,
    "embed_code": "<iframe src=\"https:\/\/www.google.com\/maps\/embed?pb=!1m18!1m12!1m3!1d3023.9430831617974!2d-73.84385868412926!3d40.719269445106846!2m3!1f0!2f0!3f0!3m2!1i1024!2i768!4f13.1!3m3!1m2!1s0x89c2609e1c08e7ad%3A0x74947fc3a4d8af6f!2s109-1+72nd+Rd%2C+Forest+Hills%2C+NY+11375%2C+Hoa+K%E1%BB%B3!5e0!3m2!1svi!2s!4v1458377830375\" width=\"1170\" height=\"450\" frameborder=\"0\" style=\"border:0\" allowfullscreen><\/iframe>",
    "contact_box_1": "123 Sky Tower, West 21th Street,<br> Suite 721, NY",
    "contact_box_i1": "map-marker",
    "contact_box_2": "+844 123 456 789<br> +844 123 456 789",
    "contact_box_i2": "phone-square",
    "contact_box_3": "contact@company.com<br> info@company.com",
    "contact_box_i3": "envelope",
    "show_multiple_currencies": true,
    "currency_format": "money_format",
    "supported_currencies": "USD EUR GBP BBD VND",
    "default_currency": "USD",
    "checkout_use_header_image": false,
    "checkout_header_image": "",
    "checkout_logo": "logo.png",
    "checkout_use_storefront_logo": "",
    "checkout_logo_image": "",
    "checkout_logo_position": "left",
    "checkout_logo_size": "medium",
    "checkout_use_body_background_image": false,
    "checkout_body_background_image": "",
    "checkout_body_background_color": "#fff",
    "checkout_input_background_color_mode": "white",
    "checkout_use_sidebar_background_image": false,
    "checkout_sidebar_background_image": "",
    "checkout_sidebar_background_color": "#fafafa",
    "checkout_heading_font": "Helvetica Neue",
    "checkout_body_font": "Helvetica Neue",
    "checkout_accent_color": "#1990C6",
    "checkout_button_color": "#1990C6",
    "checkout_error_color": "#ff6d6d",
    "select_effect_banner_2": "effect-v7",
    "banner_2_image_1_url": "#",
    "banner_2_image_2_url": "#",
    "enable_section_notice": false,
    "enable_bg_notice": true,
    "notice_autoplay": "5000",
    "enable_notice_1": true,
    "notice_text_1": "<b>SALE OFF<\/b> <span>30% <\/span>For all Products",
    "enable_notice_2": true,
    "notice_text_2": "<b>SALE OFF<\/b> <span>30% <\/span>For all Products",
    "enable_notice_3": false,
    "notice_text_3": "",
    "enable_notice_4": false,
    "notice_text_4": "",
    "home_section_6": "section-product-tab-2",
    "home_section_7": "section-banner-1-col-2",
    "home_section_8": "section-product-tab-3",
    "home_section_9": "section-banner-2-col",
    "select_effect_banner_1": "effect-v7",
    "banner_1_image_1_url": "#",
    "product_tab_title": "Mobile Phones",
    "tab_owl_checked": true,
    "tab_num": "5",
    "tab_limit": "15",
    "tab_title_1": "Apple",
    "tab_collection_1": "",
    "tab_title_2": "Samsung",
    "tab_collection_2": "",
    "tab_title_3": "Nokia",
    "tab_collection_3": "",
    "tab_title_4": "Women",
    "tab_collection_4": "",
    "product_tab_title_2": "Tabet",
    "tab_owl_checked_2": true,
    "tab_num_2": "5",
    "tab_limit_2": "8",
    "tab_title_1_2": "Tabet",
    "tab_collection_1_2": "",
    "tab_title_2_2": "Samsung",
    "tab_collection_2_2": "",
    "tab_title_3_2": "Nokia",
    "tab_collection_3_2": "",
    "tab_title_4_2": "Apple",
    "tab_collection_4_2": "",
    "select_effect_banner_1_2": "effect-v7",
    "banner_1_image_1_url_2": "#",
    "product_tab_title_3": "Bestseller",
    "tab_owl_checked_3": false,
    "tab_num_3": "5",
    "tab_limit_3": "10",
    "tab_title_1_3": "Samsung",
    "tab_collection_1_3": "",
    "tab_title_2_3": "Apple",
    "tab_collection_2_3": "",
    "tab_title_3_3": "Nokia",
    "tab_collection_3_3": "",
    "tab_title_4_3": "New Tab",
    "tab_collection_4_3": "",
    "enable_section_brand": false,
    "brand_carousel_autoplay": "8000",
    "brand_grid_item": "6",
    "brand_carousel_enable_1": true,
    "brand_carousel_url_1": "#",
    "brand_carousel_enable_2": true,
    "brand_carousel_url_2": "#",
    "brand_carousel_enable_3": true,
    "brand_carousel_url_3": "#",
    "brand_carousel_enable_4": true,
    "brand_carousel_url_4": "#",
    "brand_carousel_enable_5": true,
    "brand_carousel_url_5": "#",
    "brand_carousel_enable_6": true,
    "brand_carousel_url_6": "#",
    "brand_carousel_enable_7": true,
    "brand_carousel_url_7": "#",
    "brand_carousel_enable_8": true,
    "brand_carousel_url_8": "#",
    "brand_carousel_enable_9": true,
    "brand_carousel_url_9": "#",
    "brand_carousel_enable_10": true,
    "brand_carousel_url_10": "#",
    "enable_bg_body": "1",
    "enable_banner_1": "1",
    "url_banner_1": "",
    "enable_banner_2": "1",
    "url_banner_2": "",
    "display_price_range": true,
    "price_range_title": "Price range",
    "price_range_min": "0",
    "price_range_max": "3000",
    "price_range_prefix": "$",
    "price_range_style": "4",
    "color_border_center": "#ebebeb",
    "enable_auto_search": true,
    "button_primary_hover": "#57901f",
    "button_secondary_hover": "#000",
    "tab_title": "Mobile Phones",
    "tab_title2": "",
    "tab_owl_checked2": true,
    "tab_num2": "2",
    "tab_limit2": "8",
    "enable_bg": true,
    "banner_custom_title": "A collection of simple homewares",
    "banner_custom_des": "Nullam tincidunt dolor et eros placerat, ut imperdiet neque scelerisque. Mauris quam<br>\r\nrisus, lacinia quis diam nec, accumsan faucibus lorem. Nulla laoreet placerat ligula in <br>iaculis. Quisque feugiat ullamcorper consectetur.",
    "banner_3_image_1v2_url_2": "#",
    "banner_3_image_2v2_url_2": "#",
    "banner_3_image_3v2_url_2": "#",
    "enable_bg_new": false,
    "auto_play_test": "8000",
    "enable_bg_test": true,
    "testimonial_1": true,
    "testimonial_des_1": "Beautiful and perfect ! I have been anxiously waiting for a new theme from you guys!! :D",
    "testimonial_name_1": "John Doe",
    "testimonial_2": true,
    "testimonial_des_2": "Beautiful and perfect ! I have been anxiously waiting for a new theme from you guys!! :D",
    "testimonial_name_2": "John Doe",
    "testimonial_3": true,
    "testimonial_des_3": "Beautiful and perfect ! I have been anxiously waiting for a new theme from you guys!! :D",
    "testimonial_name_3": "John Doe",
    "testimonial_4": false,
    "testimonial_des_4": "",
    "testimonial_name_4": "",
    "testimonial_5": false,
    "testimonial_des_5": "",
    "testimonial_name_5": "",
    "testimonial_6": false,
    "testimonial_des_6": "",
    "testimonial_name_6": "",
    "bg_home_blog": true,
    "home_blogs_num": "3",
    "slide_carousel_autoplay": "8000",
    "slide_carousel_enable1": true,
    "text_slider1_txt1": "From $3",
    "text_slider1_txt2": "Shop New Arrivals",
    "text_slider1_txt3": "mini store design",
    "slider_btn1": "Shop now",
    "slider_url_btn1": "#",
    "slider_btn1_2": "Learn More",
    "slider_url_btn1_2": "#",
    "text_alignment1": "center",
    "slide_effect1": "fadeIn",
    "slide_carousel_enable2": true,
    "text_slider2_txt1": "From $3",
    "text_slider2_txt2": "Shop New Arrivals",
    "text_slider2_txt3": "mini store design",
    "slider_btn2": "Shop now",
    "slider_url_btn2": "#",
    "slider_btn2_2": "Learn More",
    "slider_url_btn2_2": "#",
    "text_alignment2": "left",
    "slide_effect2": "fadeIn",
    "slide_carousel_enable3": false,
    "text_slider3_txt1": "",
    "text_slider3_txt2": "",
    "text_slider3_txt3": "",
    "slider_btn3": "Shop now",
    "slider_url_btn3": "#",
    "slider_btn3_2": "Learn More",
    "slider_url_btn3_2": "#",
    "text_alignment3": "left",
    "slide_effect3": "bounceInDown",
    "slide_carousel_enable4": false,
    "text_slider4_txt1": "",
    "text_slider4_txt2": "",
    "text_slider4_txt3": "",
    "slider_btn4": "Shop now",
    "slider_url_btn4": "#",
    "slider_btn4_2": "Learn More",
    "slider_url_btn4_2": "#",
    "text_alignment4": "left",
    "slide_effect4": "bounceInDown",
    "home_section_full_1": false,
    "home_section_full_2": false,
    "home_section_full_3": false,
    "home_section_full_4": false,
    "home_section_full_5": false,
    "home_section_full_6": false,
    "slideshow_fullwidth": true,
    "display_share": true,
    "social_sharing_count": true,
    " menuitem_enable_1_item": false,
    "megamenu_1_column_1_title": "What's new",
    "megamenu_1_column_1_menu": "main-menu",
    "megamenu_1_column_2_title": "Trends & Events",
    "megamenu_1_column_2_menu": "footer",
    "megamenu_1_column_3_title": "Infomation",
    "megamenu_1_column_3_menu": "main-menu",
    "megamenu_1_column_4_title": "Custom Link",
    "megamenu_1_column_4_menu": "information",
    "megamenu_1_column_5_title": "Title",
    "megamenu_1_image_1_url": "#",
    " menuitem_enable_2_item": false,
    "megamenu_2_column_1_title": "",
    "megamenu_2_column_1_menu": "",
    "megamenu_2_column_2_title": "",
    "megamenu_2_column_2_menu": "",
    "megamenu_2_column_3_title": "",
    "megamenu_2_column_3_menu": "",
    "megamenu_2_image_url": "",
    "megamenu_2_column_5_title": "",
    "megamenu_2_image_1_url": "",
    " menuitem_enable_3_item": false,
    "megamenu_3_column_1_title": "",
    "megamenu_3_column_1_menu": "",
    "megamenu_3_column_2_title": "",
    "megamenu_3_column_2_menu": "",
    "megamenu_3_column_3_title": "",
    "megamenu_3_column_3_menu": "",
    "megamenu_3_image_url": "",
    "megamenu_3_column_5_title": "",
    "megamenu_3_image_1_url": "",
    " menuitem_enable_1": true,
    " menuitem_enable_2": true,
    " menuitem_enable_3": true,
    "enable_column5_1_megaone": false,
    "footer_newsletter_des": "If you wish to return or exchange items from your online order, please complete the",
    "enable_button_home": true,
    "currency_enable": true,
    "color_secondary": "#ffffff",
    "color_body_bg": "#ffffff",
    "color_next_title_block": "#ef2840",
    "enable_image_1_megaone": true,
    "home_section_space_1": "space-80",
    "home_section_space_2": "space-60",
    "home_section_space_3": "space-30",
    "home_section_space_4": "",
    "home_section_space_5": "space-30",
    "home_section_space_6": "space-60",
    "blog_full_width_per_row": "3",
    "testimonial_bg_color": "rgba(0,0,0,0)",
    "testimonial_text_color": "#ffffff",
    "select_effect_banner": "effect-v5",
    "title_banner_3_1": "Clothing",
    "sub_title_banner_3_1": "125 items",
    "banner_3_image_1_url": "#",
    "title_banner_3_2": "Bags",
    "sub_title_banner_3_2": "125 items",
    "banner_3_image_2_url": "#",
    "title_banner_3_3_1": "Shoes",
    "sub_title_banner_3_3_1": "125 items",
    "banner_3_image_3_url": "#",
    "title_banner_3_3_2": "others",
    "sub_title_banner_3_3_2": "125 items",
    "banner_3_image_3_2_url": "#",
    "slide_carousel_enable_1": true,
    "slide_carousel_url_1": "#",
    "slide_carousel_enable_2": true,
    "slide_carousel_url_2": "#",
    "slide_carousel_enable_3": true,
    "slide_carousel_url_3": "#",
    "slide_carousel_enable_4": false,
    "slide_carousel_url_4": "#",
    "slide_carousel_enable_5": false,
    "slide_carousel_url_5": "#",
    "shop_by_color_1": "#f50000",
    "shop_by_color_2": "#305885",
    "shop_by_color_3": "#fff",
    "shop_by_color_4": "#f4dfe6",
    "shop_by_color_5": "rgba(0,0,0,0)",
    "shop_by_color_6": "#485052",
    "shop_by_color_7": "#000000",
    "shop_by_color_8": "#515151",
    "shop_by_color_9": "#ff019e",
    "shop_by_color_10": "#ff019e",
    "payment_use_image": true,
    "show_icon_backhome": true,
    "slide_carousel_text_1": "",
    "slide_carousel_btn_1": "",
    "slide_carousel_text_2": "",
    "slide_carousel_btn_2": "",
    "slide_carousel_text_3": "",
    "slide_carousel_btn_3": "",
    "slide_carousel_text_4": "",
    "slide_carousel_btn_4": "Shop now",
    "slide_carousel_text_5": "",
    "slide_carousel_btn_5": "Shop now",
    "slide_carousel_effect_text": "bounceInDown",
    "slide_carousel_effect_btn": "bounceInDown",
    "size_chart_title": "Size Chart",
    "collection_1_title": "dadada",
    "collection_1_collection": "",
    "collection_2_title": "",
    "collection_2_collection": "",
    "color_topbar_bg": "#fff",
    "color_footer_social_link": "#bbbbbb",
    "color_nav_bg": "#fff",
    "brand_carousel_title": "Our brands",
    "custom_top_position": "-100px",
    "b1_url": "#",
    "b1_text_1": "Summer 2016",
    "b1_text_2": "Bag <br\/>Trending",
    "b1_position": "top-35 right-15",
    "b2_url": "#",
    "b2_text_1": "Accessories",
    "b2_text_2": "Sun Glasses",
    "b2_position": "bottom-20 left-25",
    "b3_url": "#",
    "b3_text_1": "Shop",
    "b3_text_2": "Women",
    "b3_position": "top-40 right-25",
    "b4_url": "#",
    "b4_text_1": "",
    "b4_text_2": "",
    "b4_position": "top-40 right-25",
    "b6_url": "#",
    "b6_text_1": "Shop",
    "b6_text_2": "Men",
    "b6_position": "top-40 right-40",
    "custom_center_title": "our story",
    "custom_center_content": "The key to more success is to get a massage once a week, very important, major key, cloth talk. We don’t see them, we will never see them. Surround yourself with angels. Every chance I get, I water the plants, Lion! Egg whites, turkey sausage, wheat toast, water. <br\/>\r\nOf course they don’t want us to eat our breakfast, so we are going to enjoy our breakfast. Look at the sunset, life is amazing, life is beautiful, life is what you make it. Always remember in the jungle there’s a lot of they in there, after you overcome they, you will make it to paradise.",
    "custom_center_btn": "Read More",
    "custom_center_url": "#",
    "custom_html_bottom": "",
    "box1_title": "free delivery worldwide",
    "box1_des": "on order over $50",
    "box2_title": "first purchase discount",
    "box2_des": "10% off and more good stuff",
    "box3_title": "new season sale",
    "box3_des": "up to 50% off",
    "blog_title": "Our Blog",
    "other_style_blog": true,
    "position_top": "-90px",
    "latest_posts_v1": "#f9f9f9",
    "home_section_full_7": false,
    "home_section_space_7": "",
    "home_section_full_8": false,
    "home_section_space_8": "",
    "popup_newsletter_desc": "Subscribe to our newsletters and don’t miss new arrivals, the latest fashion updates and our promotions.",
    "social_fancy_link": "",
    "footer_contact_content": "<p><strong style=\"color: #000\">Warehouse & Offices<\/strong>\r\n    <br>12345 Street name, California, USA\r\n    <br>0123 456 789 \/ 0123 456 788<\/p>\r\n<p><strong style=\"color: #000\">Retail Store<\/strong>\r\n    <br>54321 Street name, California, USA\r\n    <br>0123 456 789 \/ 0123 456 788<\/p>",
    "footer_openning_title": "Openning time",
    "footer_openning_content": "<h6 style=\"font-size: 24px;color: #000;font-size: 18px;    text-decoration: underline;\">1900 - 123 - 555<\/h6>\r\n<p>\r\n    Monday - Friday...........8.00 to 18.00\r\n    <br>\r\n    Saturday.......................9.00 to 21.00\r\n    <br>Sunday.........................10.00 to 21.00<\/p>",
    "support_block_enable": true,
    "support_block_title": "Call for support:",
    "support_block_content": "1900 - 123 - 555",
    "footer_social_enable": true,
    "footer_social_link": "<ul class=\"inline-list\">  \r\n    <li>\r\n        <a href=\"#\"><i class=\"icon icon-youtube\"><\/i><\/a>\r\n    <\/li>\r\n    <li>\r\n        <a href=\"#\"><i class=\"icon icon-google\"><\/i><\/a>\r\n    <\/li>\r\n    <li>\r\n        <a href=\"#\"><i class=\"icon icon-twitter\"><\/i><\/a>\r\n    <\/li>\r\n    <li>\r\n        <a href=\"#\"><i class=\"icon icon-facebook\"><\/i><\/a>\r\n    <\/li>\r\n<\/ul>",
    "get_in_touch_title": "PLEASE DO GET IN TOUCH!",
    "get_in_touch_content": "<p>\r\n        We'd love to hear from you - please use the form to send us your message or ideas. Or simply pop in for a cup of fresh tea and a cookie:\r\n    <\/p>\r\n    <p>\r\n        8808 Ave Dermentum, Onsectetur Adipiscing\r\n        <br>\r\n        Tortor Sagittis, CA 880986,\r\n        <br>United States<\/p>\r\n    <p>\r\n        9087S Divamus Faucibus Str.,\r\n        <br>\r\n        City name,\r\n        <br>\r\n        Postal Code,\r\n        <br>\r\n        CA 90896\r\n        <br>United States<\/p>\r\n    <p>\r\n        Email: stores@domain.com\r\n        <br>Toll-free: (1800) 000 8808<\/p>\r\n        <hr>\r\n    <p class=\"open-hours\">\r\n        Opening Hours:\r\n        <br>\r\n        Monday to Saturday: 9am - 10pm\r\n        <br>Sundays: 10am - 6pm<\/p>",
    "margin-top-section": "30",
    "margin-bottom-section": "10",
    "testimonial_title": "",
    "testimonial_bg_img": false,
    "new_arrival_url": "#",
    "featured_collection": "frontpage",
    "featured_title": "Featured Products",
    "featured_item_url": "#",
    "featured_num": "4",
    "featured_limit": "8",
    "bestseller_collection": "",
    "bestseller_title": "Bestseller Products",
    "bestseller_item_url": "#",
    "bestseller_num": "2",
    "bestseller_limit": "8",
    "custom_html_top": "<div class=\"grid\">\r\n    <div class=\"grid__item large--two-thirds medium--two-thirds\">\r\n        <a href=\"#\" class=\"effect-v3 space-20\" title=\"banner\"><img src=\"\/\/cdn.shopify.com\/s\/files\/1\/1170\/8098\/t\/2\/assets\/b1.jpg\" alt=\"\" class=\"img-responsive\"><\/a>\r\n        <div class=\"grid\">\r\n        <div class=\"grid__item large--one-half medium--one-half\">\r\n            <a href=\"#\" class=\"effect-v3\" title=\"banner\"><img src=\"\/\/cdn.shopify.com\/s\/files\/1\/1170\/8098\/t\/2\/assets\/b2.jpg\" alt=\"\" class=\"img-responsive\"><\/a>\r\n        <\/div>\r\n        <div class=\"grid__item large--one-half medium--one-half\">\r\n            <a href=\"#\" class=\"effect-v3\" title=\"banner\"><img src=\"\/\/cdn.shopify.com\/s\/files\/1\/1170\/8098\/t\/2\/assets\/b3.jpg\" alt=\"\" class=\"img-responsive\"><\/a>\r\n        <\/div>\r\n        <\/div>\r\n    <\/div>\r\n    <div class=\"grid__item large--one-third medium--one-third\">\r\n        <a href=\"#\" class=\"effect-v3\" title=\"banner\"><img src=\"\/\/cdn.shopify.com\/s\/files\/1\/1170\/8098\/t\/2\/assets\/b4.jpg\" alt=\"\" class=\"img-responsive\"><\/a>\r\n    <\/div>\r\n<\/div>",
    "custom_html_center": "<div class=\"space-top-50 space-padding-70 border border-8\">\r\n\r\n<div class=\"grid\">\r\n    <div class=\"grid__item large--two-thirds medium--two-thirds\">\r\n        <h2 class=\"section-header text-left\">Our story<\/h2>\r\n        <br>\r\n        <p>There's never been a better time for men to like clothes. But along with the rich variety of labels, styles, and stores speaking to guys of all shapes and sizes comes increased competition. In that crowded landscape, even the most storied brands have to find.\r\n        channelling history while looking towards the future.<\/p>\r\n        <br><span style=\"font-style: italic;\">by Komol Kuchkarov<\/span>\r\n    <\/div>\r\n\r\n    <div class=\"grid__item large--one-third medium--one-third\">\r\n        <img src=\"\/\/cdn.shopify.com\/s\/files\/1\/1170\/8098\/t\/2\/assets\/b5.png\" alt=\"banner\">\r\n    <\/div>\r\n<\/div>\r\n\r\n<\/div>",
    "content_for_index": [

    ]
  },
  "presets": {
    "Default": {
      "ajax_cart_method": "drawer",
      "cart_notes_enable": true,
      "color_body_bg": "#fff",
      "color_body_text": "#333333",
      "color_borders": "#e5e5e5",
      "color_footer_bg": "#f2f2f2",
      "color_footer_social_link": "#bbbbbb",
      "color_footer_text": "#636363",
      "color_primary": "#747474",
      "color_secondary": "#bbb",
      "favicon_enable": false,
      "footer_newsletter_enable": true,
      "footer_social_enable": true,
      "logo_use_image": false,
      "social_facebook_link": "",
      "social_twitter_link": ""
    }
  }
}